terncy/__init__.py
terncy/event.py
terncy/terncy.py
terncy/version.py
terncy-0.4.1.dist-info/licenses/LICENSE
terncy-0.4.1.dist-info/METADATA
terncy-0.4.1.dist-info/WHEEL
terncy-0.4.1.dist-info/top_level.txt
terncy-0.4.1.dist-info/RECORD
